newexercises/SUMMARY.md
newexercises/__init__.py
newexercises/cli.py
newexercises/config.json
newexercises/cookiecutter.json
newexercises/enums.py
newexercises/generate.py
newexercises/utils.py
newexercises/{{cookiecutter.exercise-kotlin-template}}/cookiecutter.json
newexercises/{{cookiecutter.exercise-kotlin-template}}/{{cookiecutter.exercise}}/App.{{cookiecutter.lang}}
newexercises/{{cookiecutter.exercise-kotlin-template}}/{{cookiecutter.exercise}}/App.{{cookiecutter.lang}}.txt
newexercises/{{cookiecutter.exercise-kotlin-template}}/{{cookiecutter.exercise}}/AppTest{{cookiecutter.tests_number}}.{{cookiecutter.lang}}
newexercises/{{cookiecutter.exercise-kotlin-template}}/{{cookiecutter.exercise}}/SUMMARY.md
newexercises/{{cookiecutter.exercise-kotlin-template}}/{{cookiecutter.exercise}}/exercise-config.json
newexercises/{{cookiecutter.exercise-kotlin-template}}/{{cookiecutter.exercise}}/input.txt
newexercises/{{cookiecutter.exercise-kotlin-template}}/{{cookiecutter.exercise}}/{{cookiecutter.exercise}}_instructions.md
newexercises/{{cookiecutter.exercise-template-ai}}/cookiecutter.json
newexercises/{{cookiecutter.exercise-template-ai}}/{{cookiecutter.exercise}}/SUMMARY.md
newexercises/{{cookiecutter.exercise-template-ai}}/{{cookiecutter.exercise}}/exercise-config.json
newexercises/{{cookiecutter.exercise-template-ai}}/{{cookiecutter.exercise}}/input.txt
newexercises/{{cookiecutter.exercise-template-ai}}/{{cookiecutter.exercise}}/{{cookiecutter.exercise}}_initial.{{cookiecutter.lang}}
newexercises/{{cookiecutter.exercise-template-ai}}/{{cookiecutter.exercise}}/{{cookiecutter.exercise}}_instructions.md
newexercises/{{cookiecutter.exercise-template-ai}}/{{cookiecutter.exercise}}/{{cookiecutter.exercise}}_solution.{{cookiecutter.lang}}.txt
newexercises/{{cookiecutter.exercise-template-ai}}/{{cookiecutter.exercise}}/{{cookiecutter.exercise}}_test{{cookiecutter.tests_number}}.{{cookiecutter.lang}}
newexercises/{{cookiecutter.exercise-template}}/cookiecutter.json
codelab_cookiecutter-2.0.4.dist-info/METADATA
codelab_cookiecutter-2.0.4.dist-info/WHEEL
codelab_cookiecutter-2.0.4.dist-info/entry_points.txt
codelab_cookiecutter-2.0.4.dist-info/top_level.txt
codelab_cookiecutter-2.0.4.dist-info/RECORD
